pyp_boy/__init__.py
pyp_boy/common/tools/__init__.py
pyp_boy/common/tools/errors.py
pyp_boy/gui/__init__.py
pyp_boy/gui/hacking.py
pyp_boy/main.py
pyp_boy-1.0a3.dist-info/entry_points.txt
pyp_boy-1.0a3.dist-info/WHEEL
pyp_boy-1.0a3.dist-info/METADATA
pyp_boy-1.0a3.dist-info/RECORD
